accept_types/__init__.py
accept_types/accept_types.py
accept_types-0.4.1.dist-info/LICENSE
accept_types-0.4.1.dist-info/METADATA
accept_types-0.4.1.dist-info/WHEEL
accept_types-0.4.1.dist-info/top_level.txt
accept_types-0.4.1.dist-info/RECORD
