Metadata-Version: 2.1
Name: accept-types
Version: 0.4.1
Summary: Determine the best content to send in an HTTP response
Home-page: https://bitbucket.org/tim_heap/python-accept-types
Author: Tim Heap
Author-email: tim@timheap.me
License: UNKNOWN
Platform: UNKNOWN
Classifier: Environment :: Web Environment
Classifier: Intended Audience :: Developers
Classifier: Operating System :: OS Independent
Classifier: Programming Language :: Python
Classifier: License :: OSI Approved :: MIT License
